CHANGES.txt
README.txt
TODO.txt
setup.py
.codeintel/config
Bumblebee.egg-info/SOURCES.txt
bumblebee/__init__.py
bumblebee/conditions.py
bumblebee/exceptions.py
bumblebee/rules.py
bumblebee/selectors.py
bumblebee/xml.py
bumblebee/tests/__init__.py
bumblebee/tests/test_rules.py
bumblebee/tests/test_xml.py
dist/Bumblebee-1.0a1.zip