Metadata-Version: 1.0
Name: Bumblebee
Version: 1.0a2
Summary: deliverance-like implementation that only works on html output(no theme file)
Home-page: https://github.com/vangheem/Bumblebee
Author: Nathan Van Gheem
Author-email: vangheem@gmail.com
License: UNKNOWN
Keywords: transform deliverance diazo lxml
Platform: UNKNOWN
